feelpp/benchmarking/__init__.py
feelpp/benchmarking/reframe/__init__.py
feelpp/benchmarking/reframe/__main__.py
feelpp/benchmarking/reframe/commandBuilder.py
feelpp/benchmarking/reframe/outputs.py
feelpp/benchmarking/reframe/parameters.py
feelpp/benchmarking/reframe/parser.py
feelpp/benchmarking/reframe/regression.py
feelpp/benchmarking/reframe/reporting.py
feelpp/benchmarking/reframe/resources.py
feelpp/benchmarking/reframe/scalability.py
feelpp/benchmarking/reframe/setup.py
feelpp/benchmarking/reframe/validation.py
feelpp/benchmarking/reframe/config/__init__.py
feelpp/benchmarking/reframe/config/configMachines.py
feelpp/benchmarking/reframe/config/configParameters.py
feelpp/benchmarking/reframe/config/configPlots.py
feelpp/benchmarking/reframe/config/configReader.py
feelpp/benchmarking/reframe/config/configSchemas.py
feelpp/benchmarking/reframe/config/machineConfigs/__init__.py
feelpp/benchmarking/reframe/config/machineConfigs/default/reframe.py
feelpp/benchmarking/reframe/config/machineConfigs/discoverer/__init__.py
feelpp/benchmarking/reframe/config/machineConfigs/discoverer/reframe.py
feelpp/benchmarking/reframe/config/machineConfigs/gaya/__init__.py
feelpp/benchmarking/reframe/config/machineConfigs/gaya/reframe.py
feelpp/benchmarking/reframe/config/machineConfigs/karolina/__init__.py
feelpp/benchmarking/reframe/config/machineConfigs/karolina/reframe.py
feelpp/benchmarking/reframe/config/machineConfigs/meluxina/__init__.py
feelpp/benchmarking/reframe/config/machineConfigs/meluxina/reframe.py
feelpp/benchmarking/reframe/config/machineConfigs/vega/__init__.py
feelpp/benchmarking/reframe/config/machineConfigs/vega/reframe.py
feelpp/benchmarking/report/__init__.py
feelpp/benchmarking/report/__main__.py
feelpp/benchmarking/report/parser.py
feelpp/benchmarking/report/renderer.py
feelpp/benchmarking/report/transformationFactory.py
feelpp/benchmarking/report/applications/__init__.py
feelpp/benchmarking/report/applications/application.py
feelpp_benchmarking-3.0.5.dist-info/licenses/LICENSE
feelpp_benchmarking-3.0.5.dist-info/METADATA
feelpp_benchmarking-3.0.5.dist-info/WHEEL
feelpp_benchmarking-3.0.5.dist-info/entry_points.txt
feelpp_benchmarking-3.0.5.dist-info/top_level.txt
feelpp_benchmarking-3.0.5.dist-info/RECORD
