Metadata-Version: 2.4
Name: feelpp-benchmarking
Version: 3.0.5
Summary: The Feel++ Benchmarking Project
Author-email: Christophe Prud'homme <christophe.prudhomme@cemosis.fr>, Vincent Chabannes <vincent.chabannes@cemosis.fr>, Javier Cladellas <javier.cladellas@cemosis.fr>
Project-URL: Homepage, https://github.com/feelpp/benchmarking
Project-URL: Issues, https://github.com/feelpp/benchmarking/issues
Classifier: Development Status :: 4 - Beta
Classifier: License :: OSI Approved :: MIT License
Classifier: Programming Language :: Python :: 3 :: Only
Classifier: Programming Language :: Python :: 3.7
Classifier: Programming Language :: Python :: 3.8
Classifier: Programming Language :: Python :: 3.9
Classifier: Programming Language :: Python :: 3.10
Classifier: Programming Language :: Python :: 3.11
Classifier: Programming Language :: Python :: 3.12
Requires-Python: >=3.7
License-File: LICENSE
Requires-Dist: setuptools==66.1.1
Requires-Dist: traitlets
Requires-Dist: tabulate
Requires-Dist: girder-client
Requires-Dist: pydantic
Requires-Dist: ReFrame-HPC==4.6.3
Requires-Dist: plotly
Requires-Dist: Jinja2
Requires-Dist: numpy
Requires-Dist: pandas
Requires-Dist: IPython
Provides-Extra: test
Requires-Dist: pytest; extra == "test"
Dynamic: license-file
